MakefileJiaochengCYuyanBianchengWangFix1/README.md
MakefileJiaochengCYuyanBianchengWangFix1/__init__.py
MakefileJiaochengCYuyanBianchengWangFix1/__main__.py
MakefileJiaochengCYuyanBianchengWangFix1/file.epub
MakefileJiaochengCYuyanBianchengWangFix1/index.html
MakefileJiaochengCYuyanBianchengWangFix1/css/__init__.py
MakefileJiaochengCYuyanBianchengWangFix1/css/annotations.css
MakefileJiaochengCYuyanBianchengWangFix1/css/main.css
MakefileJiaochengCYuyanBianchengWangFix1/css/normalize.css
MakefileJiaochengCYuyanBianchengWangFix1/css/popup.css
MakefileJiaochengCYuyanBianchengWangFix1/font/__init__.py
MakefileJiaochengCYuyanBianchengWangFix1/font/fontello.eot
MakefileJiaochengCYuyanBianchengWangFix1/font/fontello.svg
MakefileJiaochengCYuyanBianchengWangFix1/font/fontello.ttf
MakefileJiaochengCYuyanBianchengWangFix1/font/fontello.woff
MakefileJiaochengCYuyanBianchengWangFix1/img/__init__.py
MakefileJiaochengCYuyanBianchengWangFix1/img/annotator-glyph-sprite.png
MakefileJiaochengCYuyanBianchengWangFix1/img/annotator-icon-sprite.png
MakefileJiaochengCYuyanBianchengWangFix1/img/apple-touch-icon.png
MakefileJiaochengCYuyanBianchengWangFix1/img/cancelfullscreen.png
MakefileJiaochengCYuyanBianchengWangFix1/img/close.png
MakefileJiaochengCYuyanBianchengWangFix1/img/fullscreen.png
MakefileJiaochengCYuyanBianchengWangFix1/img/loader.gif
MakefileJiaochengCYuyanBianchengWangFix1/img/menu-icon.png
MakefileJiaochengCYuyanBianchengWangFix1/img/save.png
MakefileJiaochengCYuyanBianchengWangFix1/img/saved.png
MakefileJiaochengCYuyanBianchengWangFix1/img/settings-s.png
MakefileJiaochengCYuyanBianchengWangFix1/img/settings.png
MakefileJiaochengCYuyanBianchengWangFix1/img/star.png
MakefileJiaochengCYuyanBianchengWangFix1/js/__init__.py
MakefileJiaochengCYuyanBianchengWangFix1/js/epub.js
MakefileJiaochengCYuyanBianchengWangFix1/js/epub.min.js
MakefileJiaochengCYuyanBianchengWangFix1/js/epub.min.map
MakefileJiaochengCYuyanBianchengWangFix1/js/hooks.min.js
makefile_jiaocheng_c_yuyan_biancheng_wang_fix1-2025.3.24.0.dist-info/METADATA
makefile_jiaocheng_c_yuyan_biancheng_wang_fix1-2025.3.24.0.dist-info/WHEEL
makefile_jiaocheng_c_yuyan_biancheng_wang_fix1-2025.3.24.0.dist-info/entry_points.txt
makefile_jiaocheng_c_yuyan_biancheng_wang_fix1-2025.3.24.0.dist-info/top_level.txt
makefile_jiaocheng_c_yuyan_biancheng_wang_fix1-2025.3.24.0.dist-info/RECORD
